Metadata-Version: 2.1
Name: dynamo-db-py
Version: 0.1.6
Requires-Dist: schema==0.7.5
